neurion_ganglion/__init__.py
neurion_ganglion/blockchain/__init__.py
neurion_ganglion/blockchain/client.py
neurion_ganglion/blockchain/message.py
neurion_ganglion/blockchain/query.py
neurion_ganglion/blockchain/wallet.py
neurion_ganglion/clickhouse/__init__.py
neurion_ganglion/clickhouse/creation_script.py
neurion_ganglion/clickhouse/ion_usage.py
neurion_ganglion/clickhouse/pathway_usage.py
neurion_ganglion/custom_types/__init__.py
neurion_ganglion/custom_types/capacity.py
neurion_ganglion/custom_types/ion_type.py
neurion_ganglion/ion/__init__.py
neurion_ganglion/ion/ion.py
neurion_ganglion/ion/schema.py
neurion_ganglion/main.py
neurion_ganglion/pathway/__init__.py
neurion_ganglion/pathway/pathway.py
neurion_ganglion/pathway/schema.py
neurion_ganglion/postgres/__init__.py
neurion_ganglion/postgres/creation_script.py
neurion_ganglion/postgres/ion_usage.py
neurion_ganglion/postgres/pathway_usage.py
neurion_ganglion/server/__init__.py
neurion_ganglion/server/middlewares.py
neurion_ganglion/server/server.py
neurion_ganglion/setting/__init__.py
neurion_ganglion/utils/__init__.py
neurion_ganglion-0.13.0.dist-info/METADATA
neurion_ganglion-0.13.0.dist-info/WHEEL
neurion_ganglion-0.13.0.dist-info/RECORD
