Metadata-Version: 2.3
Name: neurion-ganglion
Version: 0.13.0
Summary: 
Author: Ryon
Author-email: zhangruiyang36@gmail.com
Requires-Python: >=3.12,<4.0
Classifier: Programming Language :: Python :: 3
Classifier: Programming Language :: Python :: 3.12
Classifier: Programming Language :: Python :: 3.13
Requires-Dist: asyncpg (>=0.30.0,<0.31.0)
Requires-Dist: clickhouse-sqlalchemy (>=0.3.2,<0.4.0)
Requires-Dist: dotenv (>=0.9.9,<0.10.0)
Requires-Dist: fastapi (>=0.115.8,<0.116.0)
Requires-Dist: neurionpy (==0.18.0)
Requires-Dist: pydantic (>=2.10.6,<3.0.0)
Requires-Dist: requests (>=2.32.3,<3.0.0)
Requires-Dist: sqlalchemy (>=2.0.38,<3.0.0)
Requires-Dist: tomli (>=2.2.1,<3.0.0)
Requires-Dist: uvicorn (>=0.34.0,<0.35.0)
